{
  "token": "t-g10462djDTPAUZA3PMRAN3BFSP7TY2VJYL5HRRVV",
  "mix_template": "B1HtdfhjKo4g4QxgNNncCtVwnth",
  "oral_template": "EbLGdZ2qYoQgpixsmQjc5EkjnNf",
  "mix_copy": {
    "doc_id": "SJLFdRabOolUMqx0zVjcdeVEnGf",
    "url": "https://scn2q8dra7p5.feishu.cn/docx/SJLFdRabOolUMqx0zVjcdeVEnGf"
  },
  "oral_copy": {
    "doc_id": "PKMiddHAXo7eQMxJEkDcq7VCnVf",
    "url": "https://scn2q8dra7p5.feishu.cn/docx/PKMiddHAXo7eQMxJEkDcq7VCnVf"
  },
  "mix_copy_id": "SJLFdRabOolUMqx0zVjcdeVEnGf",
  "oral_copy_id": "PKMiddHAXo7eQMxJEkDcq7VCnVf",
  "folder_token": "nodcnfKha8zoI7HaoGIBOg7D4Hh"
}